django_celery_email_reboot-4.2.0.dist-info/licenses/LICENSE
djcelery_email/__about__.py
djcelery_email/__init__.py
djcelery_email/backends.py
djcelery_email/conf.py
djcelery_email/models.py
djcelery_email/tasks.py
djcelery_email/utils.py
django_celery_email_reboot-4.2.0.dist-info/METADATA
django_celery_email_reboot-4.2.0.dist-info/WHEEL
django_celery_email_reboot-4.2.0.dist-info/top_level.txt
django_celery_email_reboot-4.2.0.dist-info/RECORD
