Metadata-Version: 2.4
Name: django-celery-email-reboot
Version: 4.2.0
Summary: An async Django email backend using celery (forked from django-celery-email)
Home-page: https://github.com/Panevo/django-celery-email
Author: Karlo Krakan
Author-email: karlo.krakan@panevo.com
License: BSD
Platform: any
Classifier: Development Status :: 5 - Production/Stable
Classifier: Framework :: Django
Classifier: Framework :: Django :: 4.0
Classifier: Framework :: Django :: 4.1
Classifier: Framework :: Django :: 4.2
Classifier: Framework :: Django :: 5.0
Classifier: Framework :: Django :: 5.1
Classifier: Framework :: Django :: 5.2
Classifier: Framework :: Django :: 6.0
Classifier: Operating System :: OS Independent
Classifier: Programming Language :: Python
Classifier: Programming Language :: Python :: 3
Classifier: Programming Language :: Python :: 3.10
Classifier: Programming Language :: Python :: 3.11
Classifier: Programming Language :: Python :: 3.12
Classifier: Programming Language :: Python :: 3.13
Classifier: Programming Language :: Python :: 3.14
Classifier: Intended Audience :: Developers
Classifier: License :: OSI Approved :: BSD License
Classifier: Operating System :: POSIX
Classifier: Topic :: Communications
Classifier: Topic :: Communications :: Email
Classifier: Topic :: System :: Distributed Computing
Classifier: Topic :: Software Development :: Libraries :: Python Modules
Requires-Python: >=3.10,<3.15
License-File: LICENSE
Requires-Dist: celery<5.7,>=5.2; python_version >= "3.10" and python_version <= "3.11"
Requires-Dist: celery<5.7,>=5.3; python_version >= "3.12"
Requires-Dist: Django<5.1,>=4.0; python_version == "3.10"
Requires-Dist: Django<5.3,>=4.1; python_version == "3.11"
Requires-Dist: Django<6.1,>=4.2; python_version >= "3.12"
Requires-Dist: django-appconf
Dynamic: author
Dynamic: author-email
Dynamic: classifier
Dynamic: description
Dynamic: description-content-type
Dynamic: home-page
Dynamic: license
Dynamic: license-file
Dynamic: platform
Dynamic: requires-dist
Dynamic: requires-python
Dynamic: summary
